main.py
setup.py
paws_room_acoustics_simulator.egg-info/PKG-INFO
paws_room_acoustics_simulator.egg-info/SOURCES.txt
paws_room_acoustics_simulator.egg-info/dependency_links.txt
paws_room_acoustics_simulator.egg-info/requires.txt
paws_room_acoustics_simulator.egg-info/top_level.txt